sync_dl_ytapi/__init__.py
sync_dl_ytapi/commands.py
sync_dl_ytapi/credentials.py
sync_dl_ytapi/helpers.py
sync_dl_ytapi/ytapiWrappers.py
sync_dl_ytapi-1.1.2.dist-info/LICENCE
sync_dl_ytapi-1.1.2.dist-info/METADATA
sync_dl_ytapi-1.1.2.dist-info/WHEEL
sync_dl_ytapi-1.1.2.dist-info/top_level.txt
sync_dl_ytapi-1.1.2.dist-info/RECORD
