Metadata-Version: 2.1
Name: sync-dl-ytapi
Version: 1.1.2
Summary: An addon for sync-dl, providing commands which utilize the youtube api
Home-page: https://github.com/PrinceOfPuppers/sync-dl-ytapi
Author: Joshua McPherson
Author-email: joshuamcpherson5@gmail.com
Classifier: Programming Language :: Python :: 3
Classifier: License :: OSI Approved :: MIT License
Classifier: Operating System :: OS Independent
Classifier: Environment :: Console
Classifier: Intended Audience :: End Users/Desktop
Requires-Python: >=3.6
License-File: LICENCE
Requires-Dist: sync-dl
Requires-Dist: requests
